{
	"AWSEBDockerrunVersion": 2,
	"ContainerDefinitions": [{
			"name": "client",
			"image": "maheshdwaghmare/multi-client",
			"hostname": "client",
			"essential": false
		},
		{
			"name": "server",
			"image": "maheshdwaghmare/multi-server",
			"hostname": "api",
			"essential": false
		},
		{
			"name": "worker",
			"image": "maheshdwaghmare/multi-worker",
			"hostname": "worker",
			"essential": false
		},
		{
			"name": "nginx",
			"image": "maheshdwaghmare/multi-nginx",
			"hostname": "nginx",
			"essential": true,
			"portMappings": [{
				"hostPort": 80,
				"containerPort": 80
			}],
			"links": ["client", "server"]
		}
	]
}